MANIFEST.in
README.md
requirements.txt
setup.py
paegan/__init__.py
paegan/viz/__init__.py
paegan/viz/grid.py
paegan/viz/map.py
paegan/viz/points.py
paegan/viz/timeseries.py
paegan/viz/trajectory.py
paegan_viz.egg-info/PKG-INFO
paegan_viz.egg-info/SOURCES.txt
paegan_viz.egg-info/dependency_links.txt
paegan_viz.egg-info/namespace_packages.txt
paegan_viz.egg-info/requires.txt
paegan_viz.egg-info/top_level.txt
tests/__init__.py
tests/trajectory_test.py