Metadata-Version: 1.1
Name: paegan-viz
Version: 0.3.1
Summary: Visualization packages for the Paegan library
Home-page: https://github.com/asascience-open/paegan-viz
Author: Kyle Wilcox
Author-email: kwilcox@sasascience.com
License: LICENSE.txt
Platform: UNKNOWN
Classifier: Development Status :: 3 - Alpha
Classifier: Intended Audience :: Developers
Classifier: Intended Audience :: Science/Research
Classifier: License :: OSI Approved :: GNU General Public License v3 (GPLv3)
Classifier: Operating System :: POSIX :: Linux
Classifier: Programming Language :: Python
Classifier: Topic :: Scientific/Engineering
